{
  "template": "spencer-shadley/repo-template",
  "syncedVersion": null,
  "syncedCommit": null,
  "syncedAt": null,
  "skipPaths": [],
  "_setup": "TODO(setup!): adopt-project fills these at instantiation",
  "_comment": "Template-subscription anchor. A sweep diffs template HEAD against syncedCommit and files a migration issue when structural deltas appear. After applying a migration plan, update syncedCommit+syncedAt in the same PR. skipPaths lists template paths this repo deliberately diverges from (each entry should cite an ADR or CHANGELOG 'Unchanged (intentional)' line). syncedVersion is the semantic anchor: the drift sweep files MAJOR bumps as P1 must-migrate, MINOR as P2 should-adopt, and stays SILENT on patch-only drift."
}
